pocket_w3shi/__init__.py
pocket_w3shi-0.0.2.dist-info/METADATA
pocket_w3shi-0.0.2.dist-info/WHEEL
pocket_w3shi-0.0.2.dist-info/top_level.txt
pocket_w3shi-0.0.2.dist-info/RECORD
